CapSpot/__init__.py
CapSpot/image_matcher.py
CapSpot/models/det_model.onnx
CapSpot/models/sim_model.onnx
CapSpot-0.1.0.dist-info/METADATA
CapSpot-0.1.0.dist-info/WHEEL
CapSpot-0.1.0.dist-info/top_level.txt
CapSpot-0.1.0.dist-info/RECORD
