Metadata-Version: 2.1
Name: CapSpot
Version: 0.1.0
Summary: An image matching package using ONNX models
Home-page: https://github.com/miaohancheng/CapSpot
Author: Miao Hancheng
Author-email: hanchengmiao@gmail.com
Classifier: Programming Language :: Python :: 3
Classifier: Operating System :: OS Independent
Requires-Python: >=3.7
Requires-Dist: numpy
Requires-Dist: opencv-python
Requires-Dist: Pillow
Requires-Dist: onnxruntime
